httpie_httpsig_auth.py
setup.cfg
setup.py
httpie_httpsig_auth.egg-info/PKG-INFO
httpie_httpsig_auth.egg-info/SOURCES.txt
httpie_httpsig_auth.egg-info/dependency_links.txt
httpie_httpsig_auth.egg-info/entry_points.txt
httpie_httpsig_auth.egg-info/not-zip-safe
httpie_httpsig_auth.egg-info/requires.txt
httpie_httpsig_auth.egg-info/top_level.txt