Metadata-Version: 1.1
Name: httpie-httpsig-auth
Version: 0.1.1
Summary: HTTP Signatures plugin for HTTPie.
Home-page: https://github.com/east36/httpie-http-signatures
Author: Mike Manuthu
Author-email: mmanuthu@east36.co.ke
License: BSD
Download-URL: https://github.com/east36/httpie-http-signatures
Platform: UNKNOWN
Classifier: Development Status :: 4 - Beta
Classifier: Programming Language :: Python
Classifier: Intended Audience :: Developers
Classifier: Intended Audience :: System Administrators
Classifier: Environment :: Plugins
Classifier: License :: OSI Approved :: BSD License
Classifier: Topic :: Internet :: WWW/HTTP
Classifier: Topic :: Utilities
Classifier: Topic :: System :: Networking
